[
  {
    "type": "comment",
    "lines": [
      [
        {
          "type": "COMMENT_BLOCK",
          "content": ".\\\" peter memishian -- meem@gnu.ai.mit.edu"
        }
      ],
      [
        {
          "type": "COMMENT_BLOCK",
          "content": ".\\\" $Id: insque.3,v 1.2 1996/10/30 21:03:39 meem Exp meem $"
        }
      ],
      [
        {
          "type": "COMMENT_BLOCK",
          "content": ".\\\" and Copyright (c) 2010, Michael Kerrisk <mtk.manpages@gmail.com>"
        }
      ],
      [
        {
          "type": "COMMENT_BLOCK",
          "content": ".\\\""
        }
      ],
      [
        {
          "type": "COMMENT_BLOCK",
          "content": ".\\\" %%%LICENSE_START(VERBATIM)"
        }
      ],
      [
        {
          "type": "COMMENT_BLOCK",
          "content": ".\\\" Permission is granted to make and distribute verbatim copies of this"
        }
      ],
      [
        {
          "type": "COMMENT_BLOCK",
          "content": ".\\\" manual provided the copyright notice and this permission notice are"
        }
      ],
      [
        {
          "type": "COMMENT_BLOCK",
          "content": ".\\\" preserved on all copies."
        }
      ],
      [
        {
          "type": "COMMENT_BLOCK",
          "content": ".\\\""
        }
      ],
      [
        {
          "type": "COMMENT_BLOCK",
          "content": ".\\\" Permission is granted to copy and distribute modified versions of this"
        }
      ],
      [
        {
          "type": "COMMENT_BLOCK",
          "content": ".\\\" manual under the conditions for verbatim copying, provided that the"
        }
      ],
      [
        {
          "type": "COMMENT_BLOCK",
          "content": ".\\\" entire resulting derived work is distributed under the terms of a"
        }
      ],
      [
        {
          "type": "COMMENT_BLOCK",
          "content": ".\\\" permission notice identical to this one."
        }
      ],
      [
        {
          "type": "COMMENT_BLOCK",
          "content": ".\\\""
        }
      ],
      [
        {
          "type": "COMMENT_BLOCK",
          "content": ".\\\" Since the Linux kernel and libraries are constantly changing, this"
        }
      ],
      [
        {
          "type": "COMMENT_BLOCK",
          "content": ".\\\" manual page may be incorrect or out-of-date.  The author(s) assume no"
        }
      ],
      [
        {
          "type": "COMMENT_BLOCK",
          "content": ".\\\" responsibility for errors or omissions, or for damages resulting from"
        }
      ],
      [
        {
          "type": "COMMENT_BLOCK",
          "content": ".\\\" the use of the information contained herein.  The author(s) may not"
        }
      ],
      [
        {
          "type": "COMMENT_BLOCK",
          "content": ".\\\" have taken the same level of care in the production of this manual,"
        }
      ],
      [
        {
          "type": "COMMENT_BLOCK",
          "content": ".\\\" which is licensed free of charge, as they might when working"
        }
      ],
      [
        {
          "type": "COMMENT_BLOCK",
          "content": ".\\\" professionally."
        }
      ],
      [
        {
          "type": "COMMENT_BLOCK",
          "content": ".\\\""
        }
      ],
      [
        {
          "type": "COMMENT_BLOCK",
          "content": ".\\\" Formatted or processed versions of this manual, if unaccompanied by"
        }
      ],
      [
        {
          "type": "COMMENT_BLOCK",
          "content": ".\\\" the source, must acknowledge the copyright and authors of this work."
        }
      ],
      [
        {
          "type": "COMMENT_BLOCK",
          "content": ".\\\" %%%LICENSE_END"
        }
      ],
      [
        {
          "type": "COMMENT_BLOCK",
          "content": ".\\\""
        }
      ],
      [
        {
          "type": "COMMENT_BLOCK",
          "content": ".\\\" References consulted:"
        }
      ],
      [
        {
          "type": "COMMENT_BLOCK",
          "content": ".\\\"   Linux libc source code (5.4.7)"
        }
      ],
      [
        {
          "type": "COMMENT_BLOCK",
          "content": ".\\\"   Solaris 2.x, OSF/1, and HP-UX manpages"
        }
      ],
      [
        {
          "type": "COMMENT_BLOCK",
          "content": ".\\\"   Curry's \"UNIX Systems Programming for SVR4\" (O'Reilly & Associates 1996)"
        }
      ],
      [
        {
          "type": "COMMENT_BLOCK",
          "content": ".\\\""
        }
      ],
      [
        {
          "type": "COMMENT_BLOCK",
          "content": ".\\\" Changed to POSIX, 2003-08-11, aeb+wh"
        }
      ],
      [
        {
          "type": "COMMENT_BLOCK",
          "content": ".\\\" mtk, 2010-09-09: Noted glibc 2.4 bug, added info on circular"
        }
      ],
      [
        {
          "type": "COMMENT_BLOCK",
          "content": ".\\\"\tlists, added example program"
        }
      ],
      [
        {
          "type": "COMMENT_BLOCK",
          "content": ".\\\""
        }
      ]
    ]
  },
  {
    "type": "macro",
    "lines": [
      [
        {
          "type": "MACRO_BLOCK",
          "content": ".TH",
          "translatable": false
        },
        {
          "type": "TEXT",
          "content": " INSQUE 3  2017-09-15 \"\" \"Linux Programmer's Manual\""
        }
      ]
    ]
  },
  {
    "type": "macro",
    "lines": [
      [
        {
          "type": "MACRO_BLOCK",
          "content": ".SH",
          "translatable": true
        },
        {
          "type": "TEXT",
          "content": " NAME"
        }
      ]
    ]
  },
  {
    "type": "content",
    "lines": [
      [
        {
          "type": "TEXT",
          "content": "insque, remque "
        },
        {
          "type": "ESCAPE",
          "content": "\\-"
        },
        {
          "type": "TEXT",
          "content": " insert/remove an item from a queue"
        }
      ]
    ]
  },
  {
    "type": "macro",
    "lines": [
      [
        {
          "type": "MACRO_BLOCK",
          "content": ".SH",
          "translatable": true
        },
        {
          "type": "TEXT",
          "content": " SYNOPSIS"
        }
      ]
    ]
  },
  {
    "type": "macro",
    "lines": [
      [
        {
          "type": "MACRO_BLOCK",
          "content": ".nf",
          "translatable": false
        }
      ]
    ]
  },
  {
    "type": "content",
    "lines": [
      [
        {
          "type": "MACRO_INLINE",
          "content": ".B",
          "translatable": false
        },
        {
          "type": "TEXT",
          "content": " #include <search.h>"
        }
      ]
    ]
  },
  {
    "type": "macro",
    "lines": [
      [
        {
          "type": "MACRO_BLOCK",
          "content": ".PP",
          "translatable": false
        }
      ]
    ]
  },
  {
    "type": "macro",
    "lines": [
      [
        {
          "type": "MACRO_BLOCK",
          "content": ".BI",
          "translatable": false
        },
        {
          "type": "TEXT",
          "content": " \"void insque(void *\" elem \", void *\" prev );"
        }
      ]
    ]
  },
  {
    "type": "macro",
    "lines": [
      [
        {
          "type": "MACRO_BLOCK",
          "content": ".PP",
          "translatable": false
        }
      ]
    ]
  },
  {
    "type": "macro",
    "lines": [
      [
        {
          "type": "MACRO_BLOCK",
          "content": ".BI",
          "translatable": false
        },
        {
          "type": "TEXT",
          "content": " \"void remque(void *\" elem );"
        }
      ]
    ]
  },
  {
    "type": "macro",
    "lines": [
      [
        {
          "type": "MACRO_BLOCK",
          "content": ".fi",
          "translatable": false
        }
      ]
    ]
  },
  {
    "type": "macro",
    "lines": [
      [
        {
          "type": "MACRO_BLOCK",
          "content": ".PP",
          "translatable": false
        }
      ]
    ]
  },
  {
    "type": "macro",
    "lines": [
      [
        {
          "type": "MACRO_BLOCK",
          "content": ".in",
          "translatable": false
        },
        {
          "type": "TEXT",
          "content": " -4n"
        }
      ]
    ]
  },
  {
    "type": "content",
    "lines": [
      [
        {
          "type": "TEXT",
          "content": "Feature Test Macro Requirements for glibc (see"
        }
      ],
      [
        {
          "type": "MACRO_INLINE",
          "content": ".BR",
          "translatable": false
        },
        {
          "type": "TEXT",
          "content": " feature_test_macros (7)):"
        }
      ]
    ]
  },
  {
    "type": "macro",
    "lines": [
      [
        {
          "type": "MACRO_BLOCK",
          "content": ".in",
          "translatable": false
        }
      ]
    ]
  },
  {
    "type": "macro",
    "lines": [
      [
        {
          "type": "MACRO_BLOCK",
          "content": ".PP",
          "translatable": false
        }
      ]
    ]
  },
  {
    "type": "macro",
    "lines": [
      [
        {
          "type": "MACRO_BLOCK",
          "content": ".ad",
          "translatable": false
        },
        {
          "type": "TEXT",
          "content": " l"
        }
      ]
    ]
  },
  {
    "type": "content",
    "lines": [
      [
        {
          "type": "MACRO_INLINE",
          "content": ".BR",
          "translatable": false
        },
        {
          "type": "TEXT",
          "content": " insque (),"
        }
      ],
      [
        {
          "type": "MACRO_INLINE",
          "content": ".BR",
          "translatable": false
        },
        {
          "type": "TEXT",
          "content": " remque ():"
        }
      ]
    ]
  },
  {
    "type": "macro",
    "lines": [
      [
        {
          "type": "MACRO_BLOCK",
          "content": ".RS",
          "translatable": false
        },
        {
          "type": "TEXT",
          "content": " 4"
        }
      ]
    ]
  },
  {
    "type": "content",
    "lines": [
      [
        {
          "type": "TEXT",
          "content": "_XOPEN_SOURCE"
        },
        {
          "type": "ESCAPE",
          "content": "\\ "
        },
        {
          "type": "TEXT",
          "content": ">="
        },
        {
          "type": "ESCAPE",
          "content": "\\ "
        },
        {
          "type": "TEXT",
          "content": "500"
        }
      ]
    ]
  },
  {
    "type": "comment",
    "lines": [
      [
        {
          "type": "COMMENT_BLOCK",
          "content": ".\\\"    || _XOPEN_SOURCE\\ &&\\ _XOPEN_SOURCE_EXTENDED"
        }
      ]
    ]
  },
  {
    "type": "content",
    "lines": [
      [
        {
          "type": "TEXT",
          "content": "    || /* Glibc since 2.19: */ _DEFAULT_SOURCE"
        }
      ],
      [
        {
          "type": "TEXT",
          "content": "    || /* Glibc versions <= 2.19: */ _SVID_SOURCE"
        }
      ]
    ]
  },
  {
    "type": "macro",
    "lines": [
      [
        {
          "type": "MACRO_BLOCK",
          "content": ".RE",
          "translatable": false
        }
      ]
    ]
  },
  {
    "type": "macro",
    "lines": [
      [
        {
          "type": "MACRO_BLOCK",
          "content": ".ad",
          "translatable": false
        }
      ]
    ]
  },
  {
    "type": "macro",
    "lines": [
      [
        {
          "type": "MACRO_BLOCK",
          "content": ".SH",
          "translatable": true
        },
        {
          "type": "TEXT",
          "content": " DESCRIPTION"
        }
      ]
    ]
  },
  {
    "type": "content",
    "lines": [
      [
        {
          "type": "TEXT",
          "content": "The"
        }
      ],
      [
        {
          "type": "MACRO_INLINE",
          "content": ".BR",
          "translatable": false
        },
        {
          "type": "TEXT",
          "content": " insque ()"
        }
      ],
      [
        {
          "type": "TEXT",
          "content": "and"
        }
      ],
      [
        {
          "type": "MACRO_INLINE",
          "content": ".BR",
          "translatable": false
        },
        {
          "type": "TEXT",
          "content": " remque ()"
        }
      ],
      [
        {
          "type": "TEXT",
          "content": "functions manipulate doubly-linked lists."
        }
      ],
      [
        {
          "type": "TEXT",
          "content": "Each element in the list is a structure of"
        }
      ],
      [
        {
          "type": "TEXT",
          "content": "which the first two elements are a forward and a"
        }
      ],
      [
        {
          "type": "TEXT",
          "content": "backward pointer."
        }
      ],
      [
        {
          "type": "TEXT",
          "content": "The linked list may be linear (i.e., NULL forward pointer at"
        }
      ],
      [
        {
          "type": "TEXT",
          "content": "the end of the list and NULL backward pointer at the start of the list)"
        }
      ],
      [
        {
          "type": "TEXT",
          "content": "or circular."
        }
      ]
    ]
  },
  {
    "type": "macro",
    "lines": [
      [
        {
          "type": "MACRO_BLOCK",
          "content": ".PP",
          "translatable": false
        }
      ]
    ]
  },
  {
    "type": "content",
    "lines": [
      [
        {
          "type": "TEXT",
          "content": "The"
        }
      ],
      [
        {
          "type": "MACRO_INLINE",
          "content": ".BR",
          "translatable": false
        },
        {
          "type": "TEXT",
          "content": " insque ()"
        }
      ],
      [
        {
          "type": "TEXT",
          "content": "function inserts the element pointed to by "
        },
        {
          "type": "ESCAPE",
          "content": "\\f"
        },
        {
          "type": "TEXT",
          "content": "Ielem"
        },
        {
          "type": "ESCAPE",
          "content": "\\f"
        },
        {
          "type": "TEXT",
          "content": "P"
        }
      ],
      [
        {
          "type": "TEXT",
          "content": "immediately after the element pointed to by "
        },
        {
          "type": "ESCAPE",
          "content": "\\f"
        },
        {
          "type": "TEXT",
          "content": "Iprev"
        },
        {
          "type": "ESCAPE",
          "content": "\\f"
        },
        {
          "type": "TEXT",
          "content": "P."
        }
      ]
    ]
  },
  {
    "type": "macro",
    "lines": [
      [
        {
          "type": "MACRO_BLOCK",
          "content": ".PP",
          "translatable": false
        }
      ]
    ]
  },
  {
    "type": "content",
    "lines": [
      [
        {
          "type": "TEXT",
          "content": "If the list is linear, then the call"
        }
      ],
      [
        {
          "type": "MACRO_INLINE",
          "content": ".I",
          "translatable": false
        },
        {
          "type": "TEXT",
          "content": " \"insque(elem, NULL)\""
        }
      ],
      [
        {
          "type": "TEXT",
          "content": "can be used to insert the initial list element,"
        }
      ],
      [
        {
          "type": "TEXT",
          "content": "and the call sets the forward and backward pointers of"
        }
      ],
      [
        {
          "type": "MACRO_INLINE",
          "content": ".I",
          "translatable": false
        },
        {
          "type": "TEXT",
          "content": " elem"
        }
      ],
      [
        {
          "type": "TEXT",
          "content": "to NULL."
        }
      ]
    ]
  },
  {
    "type": "macro",
    "lines": [
      [
        {
          "type": "MACRO_BLOCK",
          "content": ".PP",
          "translatable": false
        }
      ]
    ]
  },
  {
    "type": "content",
    "lines": [
      [
        {
          "type": "TEXT",
          "content": "If the list is circular,"
        }
      ],
      [
        {
          "type": "TEXT",
          "content": "the caller should ensure that the forward and backward pointers of the"
        }
      ],
      [
        {
          "type": "TEXT",
          "content": "first element are initialized to point to that element,"
        }
      ],
      [
        {
          "type": "TEXT",
          "content": "and the"
        }
      ],
      [
        {
          "type": "MACRO_INLINE",
          "content": ".I",
          "translatable": false
        },
        {
          "type": "TEXT",
          "content": " prev"
        }
      ],
      [
        {
          "type": "TEXT",
          "content": "argument of the"
        }
      ],
      [
        {
          "type": "MACRO_INLINE",
          "content": ".BR",
          "translatable": false
        },
        {
          "type": "TEXT",
          "content": " insque ()"
        }
      ],
      [
        {
          "type": "TEXT",
          "content": "call should also point to the element."
        }
      ]
    ]
  },
  {
    "type": "macro",
    "lines": [
      [
        {
          "type": "MACRO_BLOCK",
          "content": ".PP",
          "translatable": false
        }
      ]
    ]
  },
  {
    "type": "content",
    "lines": [
      [
        {
          "type": "TEXT",
          "content": "The"
        }
      ],
      [
        {
          "type": "MACRO_INLINE",
          "content": ".BR",
          "translatable": false
        },
        {
          "type": "TEXT",
          "content": " remque ()"
        }
      ],
      [
        {
          "type": "TEXT",
          "content": "function removes the element pointed to by "
        },
        {
          "type": "ESCAPE",
          "content": "\\f"
        },
        {
          "type": "TEXT",
          "content": "Ielem"
        },
        {
          "type": "ESCAPE",
          "content": "\\f"
        },
        {
          "type": "TEXT",
          "content": "P from the"
        }
      ],
      [
        {
          "type": "TEXT",
          "content": "doubly-linked list."
        }
      ]
    ]
  },
  {
    "type": "macro",
    "lines": [
      [
        {
          "type": "MACRO_BLOCK",
          "content": ".SH",
          "translatable": true
        },
        {
          "type": "TEXT",
          "content": " ATTRIBUTES"
        }
      ]
    ]
  },
  {
    "type": "content",
    "lines": [
      [
        {
          "type": "TEXT",
          "content": "For an explanation of the terms used in this section, see"
        }
      ],
      [
        {
          "type": "MACRO_INLINE",
          "content": ".BR",
          "translatable": false
        },
        {
          "type": "TEXT",
          "content": " attributes (7)."
        }
      ]
    ]
  },
  {
    "type": "macro",
    "lines": [
      [
        {
          "type": "MACRO_BLOCK",
          "content": ".TS",
          "translatable": false
        }
      ]
    ]
  },
  {
    "type": "content",
    "lines": [
      [
        {
          "type": "TEXT",
          "content": "allbox;"
        }
      ],
      [
        {
          "type": "TEXT",
          "content": "lb lb lb"
        }
      ],
      [
        {
          "type": "TEXT",
          "content": "l l l."
        }
      ],
      [
        {
          "type": "TEXT",
          "content": "Interface\tAttribute\tValue"
        }
      ],
      [
        {
          "type": "TEXT",
          "content": "T{"
        }
      ],
      [
        {
          "type": "MACRO_INLINE",
          "content": ".BR",
          "translatable": false
        },
        {
          "type": "TEXT",
          "content": " insque (),"
        }
      ],
      [
        {
          "type": "MACRO_INLINE",
          "content": ".BR",
          "translatable": false
        },
        {
          "type": "TEXT",
          "content": " remque ()"
        }
      ],
      [
        {
          "type": "TEXT",
          "content": "T}\tThread safety\tMT-Safe"
        }
      ]
    ]
  },
  {
    "type": "macro",
    "lines": [
      [
        {
          "type": "MACRO_BLOCK",
          "content": ".TE",
          "translatable": true
        }
      ]
    ]
  },
  {
    "type": "macro",
    "lines": [
      [
        {
          "type": "MACRO_BLOCK",
          "content": ".sp",
          "translatable": false
        },
        {
          "type": "TEXT",
          "content": " 1"
        }
      ]
    ]
  },
  {
    "type": "macro",
    "lines": [
      [
        {
          "type": "MACRO_BLOCK",
          "content": ".SH",
          "translatable": true
        },
        {
          "type": "TEXT",
          "content": " CONFORMING TO"
        }
      ]
    ]
  },
  {
    "type": "content",
    "lines": [
      [
        {
          "type": "TEXT",
          "content": "POSIX.1-2001, POSIX.1-2008."
        }
      ]
    ]
  },
  {
    "type": "macro",
    "lines": [
      [
        {
          "type": "MACRO_BLOCK",
          "content": ".SH",
          "translatable": true
        },
        {
          "type": "TEXT",
          "content": " NOTES"
        }
      ]
    ]
  },
  {
    "type": "content",
    "lines": [
      [
        {
          "type": "TEXT",
          "content": "On ancient systems,"
        }
      ]
    ]
  },
  {
    "type": "comment",
    "lines": [
      [
        {
          "type": "COMMENT_BLOCK",
          "content": ".\\\" e.g., SunOS, Linux libc4 and libc5"
        }
      ]
    ]
  },
  {
    "type": "content",
    "lines": [
      [
        {
          "type": "TEXT",
          "content": "the arguments of these functions were of type "
        },
        {
          "type": "ESCAPE",
          "content": "\\f"
        },
        {
          "type": "TEXT",
          "content": "Istruct qelem *"
        },
        {
          "type": "ESCAPE",
          "content": "\\f"
        },
        {
          "type": "TEXT",
          "content": "P,"
        }
      ],
      [
        {
          "type": "TEXT",
          "content": "defined as:"
        }
      ]
    ]
  },
  {
    "type": "macro",
    "lines": [
      [
        {
          "type": "MACRO_BLOCK",
          "content": ".PP",
          "translatable": false
        }
      ]
    ]
  },
  {
    "type": "macro",
    "lines": [
      [
        {
          "type": "MACRO_BLOCK",
          "content": ".in",
          "translatable": false
        },
        {
          "type": "TEXT",
          "content": " +4n"
        }
      ]
    ]
  },
  {
    "type": "content",
    "lines": [
      [
        {
          "type": "TEXT",
          "content": ".EX"
        }
      ],
      [
        {
          "type": "TEXT",
          "content": "struct qelem {"
        }
      ],
      [
        {
          "type": "TEXT",
          "content": "    struct qelem *q_forw;"
        }
      ],
      [
        {
          "type": "TEXT",
          "content": "    struct qelem *q_back;"
        }
      ],
      [
        {
          "type": "TEXT",
          "content": "    char          q_data[1];"
        }
      ],
      [
        {
          "type": "TEXT",
          "content": "};"
        }
      ],
      [
        {
          "type": "TEXT",
          "content": ".EE"
        }
      ]
    ]
  },
  {
    "type": "macro",
    "lines": [
      [
        {
          "type": "MACRO_BLOCK",
          "content": ".in",
          "translatable": false
        }
      ]
    ]
  },
  {
    "type": "macro",
    "lines": [
      [
        {
          "type": "MACRO_BLOCK",
          "content": ".PP",
          "translatable": false
        }
      ]
    ]
  },
  {
    "type": "content",
    "lines": [
      [
        {
          "type": "TEXT",
          "content": "This is still what you will get if"
        }
      ],
      [
        {
          "type": "MACRO_INLINE",
          "content": ".B",
          "translatable": false
        },
        {
          "type": "TEXT",
          "content": " _GNU_SOURCE"
        }
      ],
      [
        {
          "type": "TEXT",
          "content": "is defined before"
        }
      ],
      [
        {
          "type": "TEXT",
          "content": "including "
        },
        {
          "type": "ESCAPE",
          "content": "\\f"
        },
        {
          "type": "TEXT",
          "content": "I<search.h>"
        },
        {
          "type": "ESCAPE",
          "content": "\\f"
        },
        {
          "type": "TEXT",
          "content": "P."
        }
      ]
    ]
  },
  {
    "type": "macro",
    "lines": [
      [
        {
          "type": "MACRO_BLOCK",
          "content": ".PP",
          "translatable": false
        }
      ]
    ]
  },
  {
    "type": "content",
    "lines": [
      [
        {
          "type": "TEXT",
          "content": "The location of the prototypes for these functions differs among several"
        }
      ],
      [
        {
          "type": "TEXT",
          "content": "versions of UNIX."
        }
      ],
      [
        {
          "type": "TEXT",
          "content": "The above is the POSIX version."
        }
      ],
      [
        {
          "type": "TEXT",
          "content": "Some systems place them in "
        },
        {
          "type": "ESCAPE",
          "content": "\\f"
        },
        {
          "type": "TEXT",
          "content": "I<string.h>"
        },
        {
          "type": "ESCAPE",
          "content": "\\f"
        },
        {
          "type": "TEXT",
          "content": "P."
        }
      ]
    ]
  },
  {
    "type": "comment",
    "lines": [
      [
        {
          "type": "COMMENT_BLOCK",
          "content": ".\\\" Linux libc4 and libc 5 placed them"
        }
      ],
      [
        {
          "type": "COMMENT_BLOCK",
          "content": ".\\\" in \\fI<stdlib.h>\\fP."
        }
      ]
    ]
  },
  {
    "type": "macro",
    "lines": [
      [
        {
          "type": "MACRO_BLOCK",
          "content": ".SH",
          "translatable": true
        },
        {
          "type": "TEXT",
          "content": " BUGS"
        }
      ]
    ]
  },
  {
    "type": "content",
    "lines": [
      [
        {
          "type": "TEXT",
          "content": "In glibc 2.4 and earlier, it was not possible to specify"
        }
      ],
      [
        {
          "type": "MACRO_INLINE",
          "content": ".I",
          "translatable": false
        },
        {
          "type": "TEXT",
          "content": " prev"
        }
      ],
      [
        {
          "type": "TEXT",
          "content": "as NULL."
        }
      ],
      [
        {
          "type": "TEXT",
          "content": "Consequently, to build a linear list, the caller had to build a list"
        }
      ],
      [
        {
          "type": "TEXT",
          "content": "using an initial call that contained the first two elements of the list,"
        }
      ],
      [
        {
          "type": "TEXT",
          "content": "with the forward and backward pointers in each element suitably initialized."
        }
      ]
    ]
  },
  {
    "type": "macro",
    "lines": [
      [
        {
          "type": "MACRO_BLOCK",
          "content": ".SH",
          "translatable": true
        },
        {
          "type": "TEXT",
          "content": " EXAMPLE"
        }
      ]
    ]
  },
  {
    "type": "content",
    "lines": [
      [
        {
          "type": "TEXT",
          "content": "The program below demonstrates the use of"
        }
      ],
      [
        {
          "type": "MACRO_INLINE",
          "content": ".BR",
          "translatable": false
        },
        {
          "type": "TEXT",
          "content": " insque ()."
        }
      ],
      [
        {
          "type": "TEXT",
          "content": "Here is an example run of the program:"
        }
      ]
    ]
  },
  {
    "type": "macro",
    "lines": [
      [
        {
          "type": "MACRO_BLOCK",
          "content": ".PP",
          "translatable": false
        }
      ]
    ]
  },
  {
    "type": "macro",
    "lines": [
      [
        {
          "type": "MACRO_BLOCK",
          "content": ".in",
          "translatable": false
        },
        {
          "type": "TEXT",
          "content": " +4n"
        }
      ]
    ]
  },
  {
    "type": "content",
    "lines": [
      [
        {
          "type": "TEXT",
          "content": ".EX"
        }
      ],
      [
        {
          "type": "MACRO_INLINE",
          "content": ".RB",
          "translatable": false
        },
        {
          "type": "TEXT",
          "content": " \"$ \" \"./a.out -c a b c\""
        }
      ],
      [
        {
          "type": "TEXT",
          "content": "Traversing completed list:"
        }
      ],
      [
        {
          "type": "TEXT",
          "content": "    a"
        }
      ],
      [
        {
          "type": "TEXT",
          "content": "    b"
        }
      ],
      [
        {
          "type": "TEXT",
          "content": "    c"
        }
      ],
      [
        {
          "type": "TEXT",
          "content": "That was a circular list"
        }
      ],
      [
        {
          "type": "TEXT",
          "content": ".EE"
        }
      ]
    ]
  },
  {
    "type": "macro",
    "lines": [
      [
        {
          "type": "MACRO_BLOCK",
          "content": ".in",
          "translatable": false
        }
      ]
    ]
  },
  {
    "type": "macro",
    "lines": [
      [
        {
          "type": "MACRO_BLOCK",
          "content": ".SS",
          "translatable": true
        },
        {
          "type": "TEXT",
          "content": " Program source"
        }
      ]
    ]
  },
  {
    "type": "content",
    "lines": [
      [
        {
          "type": "ESCAPE",
          "content": "\\&"
        }
      ],
      [
        {
          "type": "TEXT",
          "content": ".EX"
        }
      ],
      [
        {
          "type": "TEXT",
          "content": "#include <stdio.h>"
        }
      ],
      [
        {
          "type": "TEXT",
          "content": "#include <stdlib.h>"
        }
      ],
      [
        {
          "type": "TEXT",
          "content": "#include <unistd.h>"
        }
      ],
      [
        {
          "type": "TEXT",
          "content": "#include <search.h>"
        }
      ]
    ]
  },
  {
    "type": "empty",
    "lines": [
      [

      ]
    ]
  },
  {
    "type": "content",
    "lines": [
      [
        {
          "type": "TEXT",
          "content": "struct element {"
        }
      ],
      [
        {
          "type": "TEXT",
          "content": "    struct element *forward;"
        }
      ],
      [
        {
          "type": "TEXT",
          "content": "    struct element *backward;"
        }
      ],
      [
        {
          "type": "TEXT",
          "content": "    char *name;"
        }
      ],
      [
        {
          "type": "TEXT",
          "content": "};"
        }
      ]
    ]
  },
  {
    "type": "empty",
    "lines": [
      [

      ]
    ]
  },
  {
    "type": "content",
    "lines": [
      [
        {
          "type": "TEXT",
          "content": "static struct element *"
        }
      ],
      [
        {
          "type": "TEXT",
          "content": "new_element(void)"
        }
      ],
      [
        {
          "type": "TEXT",
          "content": "{"
        }
      ],
      [
        {
          "type": "TEXT",
          "content": "    struct element *e;"
        }
      ]
    ]
  },
  {
    "type": "empty",
    "lines": [
      [

      ]
    ]
  },
  {
    "type": "content",
    "lines": [
      [
        {
          "type": "TEXT",
          "content": "    e = malloc(sizeof(struct element));"
        }
      ],
      [
        {
          "type": "TEXT",
          "content": "    if (e == NULL) {"
        }
      ],
      [
        {
          "type": "TEXT",
          "content": "        fprintf(stderr, \"malloc() failed"
        },
        {
          "type": "ESCAPE",
          "content": "\\\\"
        },
        {
          "type": "TEXT",
          "content": "n\");"
        }
      ],
      [
        {
          "type": "TEXT",
          "content": "        exit(EXIT_FAILURE);"
        }
      ],
      [
        {
          "type": "TEXT",
          "content": "    }"
        }
      ]
    ]
  },
  {
    "type": "empty",
    "lines": [
      [

      ]
    ]
  },
  {
    "type": "content",
    "lines": [
      [
        {
          "type": "TEXT",
          "content": "    return e;"
        }
      ],
      [
        {
          "type": "TEXT",
          "content": "}"
        }
      ]
    ]
  },
  {
    "type": "empty",
    "lines": [
      [

      ]
    ]
  },
  {
    "type": "content",
    "lines": [
      [
        {
          "type": "TEXT",
          "content": "int"
        }
      ],
      [
        {
          "type": "TEXT",
          "content": "main(int argc, char *argv[])"
        }
      ],
      [
        {
          "type": "TEXT",
          "content": "{"
        }
      ],
      [
        {
          "type": "TEXT",
          "content": "    struct element *first, *elem, *prev;"
        }
      ],
      [
        {
          "type": "TEXT",
          "content": "    int circular, opt, errfnd;"
        }
      ]
    ]
  },
  {
    "type": "empty",
    "lines": [
      [

      ]
    ]
  },
  {
    "type": "content",
    "lines": [
      [
        {
          "type": "TEXT",
          "content": "    /* The \""
        },
        {
          "type": "ESCAPE",
          "content": "\\-"
        },
        {
          "type": "TEXT",
          "content": "c\" command"
        },
        {
          "type": "ESCAPE",
          "content": "\\-"
        },
        {
          "type": "TEXT",
          "content": "line option can be used to specify that the"
        }
      ],
      [
        {
          "type": "TEXT",
          "content": "       list is circular */"
        }
      ]
    ]
  },
  {
    "type": "empty",
    "lines": [
      [

      ]
    ]
  },
  {
    "type": "content",
    "lines": [
      [
        {
          "type": "TEXT",
          "content": "    errfnd = 0;"
        }
      ],
      [
        {
          "type": "TEXT",
          "content": "    circular = 0;"
        }
      ],
      [
        {
          "type": "TEXT",
          "content": "    while ((opt = getopt(argc, argv, \"c\")) != "
        },
        {
          "type": "ESCAPE",
          "content": "\\-"
        },
        {
          "type": "TEXT",
          "content": "1) {"
        }
      ],
      [
        {
          "type": "TEXT",
          "content": "        switch (opt) {"
        }
      ],
      [
        {
          "type": "TEXT",
          "content": "        case 'c':"
        }
      ],
      [
        {
          "type": "TEXT",
          "content": "            circular = 1;"
        }
      ],
      [
        {
          "type": "TEXT",
          "content": "            break;"
        }
      ],
      [
        {
          "type": "TEXT",
          "content": "        default:"
        }
      ],
      [
        {
          "type": "TEXT",
          "content": "            errfnd = 1;"
        }
      ],
      [
        {
          "type": "TEXT",
          "content": "            break;"
        }
      ],
      [
        {
          "type": "TEXT",
          "content": "        }"
        }
      ],
      [
        {
          "type": "TEXT",
          "content": "    }"
        }
      ]
    ]
  },
  {
    "type": "empty",
    "lines": [
      [

      ]
    ]
  },
  {
    "type": "content",
    "lines": [
      [
        {
          "type": "TEXT",
          "content": "    if (errfnd || optind >= argc) {"
        }
      ],
      [
        {
          "type": "TEXT",
          "content": "        fprintf(stderr,  \"Usage: %s ["
        },
        {
          "type": "ESCAPE",
          "content": "\\-"
        },
        {
          "type": "TEXT",
          "content": "c] string..."
        },
        {
          "type": "ESCAPE",
          "content": "\\\\"
        },
        {
          "type": "TEXT",
          "content": "n\", argv[0]);"
        }
      ],
      [
        {
          "type": "TEXT",
          "content": "        exit(EXIT_FAILURE);"
        }
      ],
      [
        {
          "type": "TEXT",
          "content": "    }"
        }
      ]
    ]
  },
  {
    "type": "empty",
    "lines": [
      [

      ]
    ]
  },
  {
    "type": "content",
    "lines": [
      [
        {
          "type": "TEXT",
          "content": "    /* Create first element and place it in the linked list */"
        }
      ]
    ]
  },
  {
    "type": "empty",
    "lines": [
      [

      ]
    ]
  },
  {
    "type": "content",
    "lines": [
      [
        {
          "type": "TEXT",
          "content": "    elem = new_element();"
        }
      ],
      [
        {
          "type": "TEXT",
          "content": "    first = elem;"
        }
      ]
    ]
  },
  {
    "type": "empty",
    "lines": [
      [

      ]
    ]
  },
  {
    "type": "content",
    "lines": [
      [
        {
          "type": "TEXT",
          "content": "    elem"
        },
        {
          "type": "ESCAPE",
          "content": "\\-"
        },
        {
          "type": "TEXT",
          "content": ">name = argv[optind];"
        }
      ]
    ]
  },
  {
    "type": "empty",
    "lines": [
      [

      ]
    ]
  },
  {
    "type": "content",
    "lines": [
      [
        {
          "type": "TEXT",
          "content": "    if (circular) {"
        }
      ],
      [
        {
          "type": "TEXT",
          "content": "        elem"
        },
        {
          "type": "ESCAPE",
          "content": "\\-"
        },
        {
          "type": "TEXT",
          "content": ">forward = elem;"
        }
      ],
      [
        {
          "type": "TEXT",
          "content": "        elem"
        },
        {
          "type": "ESCAPE",
          "content": "\\-"
        },
        {
          "type": "TEXT",
          "content": ">backward = elem;"
        }
      ],
      [
        {
          "type": "TEXT",
          "content": "        insque(elem, elem);"
        }
      ],
      [
        {
          "type": "TEXT",
          "content": "    } else {"
        }
      ],
      [
        {
          "type": "TEXT",
          "content": "        insque(elem, NULL);"
        }
      ],
      [
        {
          "type": "TEXT",
          "content": "    }"
        }
      ]
    ]
  },
  {
    "type": "empty",
    "lines": [
      [

      ]
    ]
  },
  {
    "type": "content",
    "lines": [
      [
        {
          "type": "TEXT",
          "content": "    /* Add remaining command"
        },
        {
          "type": "ESCAPE",
          "content": "\\-"
        },
        {
          "type": "TEXT",
          "content": "line arguments as list elements */"
        }
      ]
    ]
  },
  {
    "type": "empty",
    "lines": [
      [

      ]
    ]
  },
  {
    "type": "content",
    "lines": [
      [
        {
          "type": "TEXT",
          "content": "    while (++optind < argc) {"
        }
      ],
      [
        {
          "type": "TEXT",
          "content": "        prev = elem;"
        }
      ]
    ]
  },
  {
    "type": "empty",
    "lines": [
      [

      ]
    ]
  },
  {
    "type": "content",
    "lines": [
      [
        {
          "type": "TEXT",
          "content": "        elem = new_element();"
        }
      ],
      [
        {
          "type": "TEXT",
          "content": "        elem"
        },
        {
          "type": "ESCAPE",
          "content": "\\-"
        },
        {
          "type": "TEXT",
          "content": ">name = argv[optind];"
        }
      ],
      [
        {
          "type": "TEXT",
          "content": "        insque(elem, prev);"
        }
      ],
      [
        {
          "type": "TEXT",
          "content": "    }"
        }
      ]
    ]
  },
  {
    "type": "empty",
    "lines": [
      [

      ]
    ]
  },
  {
    "type": "content",
    "lines": [
      [
        {
          "type": "TEXT",
          "content": "    /* Traverse the list from the start, printing element names */"
        }
      ]
    ]
  },
  {
    "type": "empty",
    "lines": [
      [

      ]
    ]
  },
  {
    "type": "content",
    "lines": [
      [
        {
          "type": "TEXT",
          "content": "    printf(\"Traversing completed list:"
        },
        {
          "type": "ESCAPE",
          "content": "\\\\"
        },
        {
          "type": "TEXT",
          "content": "n\");"
        }
      ],
      [
        {
          "type": "TEXT",
          "content": "    elem = first;"
        }
      ],
      [
        {
          "type": "TEXT",
          "content": "    do {"
        }
      ],
      [
        {
          "type": "TEXT",
          "content": "        printf(\"    %s"
        },
        {
          "type": "ESCAPE",
          "content": "\\\\"
        },
        {
          "type": "TEXT",
          "content": "n\", elem"
        },
        {
          "type": "ESCAPE",
          "content": "\\-"
        },
        {
          "type": "TEXT",
          "content": ">name);"
        }
      ],
      [
        {
          "type": "TEXT",
          "content": "        elem = elem"
        },
        {
          "type": "ESCAPE",
          "content": "\\-"
        },
        {
          "type": "TEXT",
          "content": ">forward;"
        }
      ],
      [
        {
          "type": "TEXT",
          "content": "    } while (elem != NULL && elem != first);"
        }
      ]
    ]
  },
  {
    "type": "empty",
    "lines": [
      [

      ]
    ]
  },
  {
    "type": "content",
    "lines": [
      [
        {
          "type": "TEXT",
          "content": "    if (elem == first)"
        }
      ],
      [
        {
          "type": "TEXT",
          "content": "        printf(\"That was a circular list"
        },
        {
          "type": "ESCAPE",
          "content": "\\\\"
        },
        {
          "type": "TEXT",
          "content": "n\");"
        }
      ]
    ]
  },
  {
    "type": "empty",
    "lines": [
      [

      ]
    ]
  },
  {
    "type": "content",
    "lines": [
      [
        {
          "type": "TEXT",
          "content": "    exit(EXIT_SUCCESS);"
        }
      ],
      [
        {
          "type": "TEXT",
          "content": "}"
        }
      ],
      [
        {
          "type": "TEXT",
          "content": ".EE"
        }
      ]
    ]
  },
  {
    "type": "macro",
    "lines": [
      [
        {
          "type": "MACRO_BLOCK",
          "content": ".SH",
          "translatable": true
        },
        {
          "type": "TEXT",
          "content": " SEE ALSO"
        }
      ]
    ]
  },
  {
    "type": "content",
    "lines": [
      [
        {
          "type": "MACRO_INLINE",
          "content": ".BR",
          "translatable": false
        },
        {
          "type": "TEXT",
          "content": " queue (3)"
        }
      ]
    ]
  }
]
