[
  {
    "type": "comment",
    "lines": [
      [
        {
          "type": "COMMENT_BLOCK",
          "content": ".\\\" This manpage copyright 1998 by Andi Kleen."
        }
      ],
      [
        {
          "type": "COMMENT_BLOCK",
          "content": ".\\\""
        }
      ],
      [
        {
          "type": "COMMENT_BLOCK",
          "content": ".\\\" %%%LICENSE_START(GPL_NOVERSION_ONELINE)"
        }
      ],
      [
        {
          "type": "COMMENT_BLOCK",
          "content": ".\\\" Subject to the GPL."
        }
      ],
      [
        {
          "type": "COMMENT_BLOCK",
          "content": ".\\\" %%%LICENSE_END"
        }
      ],
      [
        {
          "type": "COMMENT_BLOCK",
          "content": ".\\\""
        }
      ],
      [
        {
          "type": "COMMENT_BLOCK",
          "content": ".\\\" Based on the original comments from Alexey Kuznetsov"
        }
      ],
      [
        {
          "type": "COMMENT_BLOCK",
          "content": ".\\\" $Id: netlink.3,v 1.1 1999/05/14 17:17:24 freitag Exp $"
        }
      ],
      [
        {
          "type": "COMMENT_BLOCK",
          "content": ".\\\""
        }
      ]
    ]
  },
  {
    "type": "macro",
    "lines": [
      [
        {
          "type": "MACRO_BLOCK",
          "content": ".TH",
          "translatable": false
        },
        {
          "type": "TEXT",
          "content": " NETLINK 3 2014-03-20 \"GNU\" \"Linux Programmer's Manual\""
        }
      ]
    ]
  },
  {
    "type": "macro",
    "lines": [
      [
        {
          "type": "MACRO_BLOCK",
          "content": ".SH",
          "translatable": true
        },
        {
          "type": "TEXT",
          "content": " NAME"
        }
      ]
    ]
  },
  {
    "type": "content",
    "lines": [
      [
        {
          "type": "TEXT",
          "content": "netlink "
        },
        {
          "type": "ESCAPE",
          "content": "\\-"
        },
        {
          "type": "TEXT",
          "content": " Netlink macros"
        }
      ]
    ]
  },
  {
    "type": "macro",
    "lines": [
      [
        {
          "type": "MACRO_BLOCK",
          "content": ".SH",
          "translatable": true
        },
        {
          "type": "TEXT",
          "content": " SYNOPSIS"
        }
      ]
    ]
  },
  {
    "type": "macro",
    "lines": [
      [
        {
          "type": "MACRO_BLOCK",
          "content": ".nf",
          "translatable": false
        }
      ]
    ]
  },
  {
    "type": "content",
    "lines": [
      [
        {
          "type": "MACRO_INLINE",
          "content": ".B",
          "translatable": false
        },
        {
          "type": "TEXT",
          "content": " #include <asm/types.h>"
        }
      ],
      [
        {
          "type": "MACRO_INLINE",
          "content": ".B",
          "translatable": false
        },
        {
          "type": "TEXT",
          "content": " #include <linux/netlink.h>"
        }
      ]
    ]
  },
  {
    "type": "macro",
    "lines": [
      [
        {
          "type": "MACRO_BLOCK",
          "content": ".PP",
          "translatable": false
        }
      ]
    ]
  },
  {
    "type": "macro",
    "lines": [
      [
        {
          "type": "MACRO_BLOCK",
          "content": ".BI",
          "translatable": false
        },
        {
          "type": "TEXT",
          "content": " \"int NLMSG_ALIGN(size_t \" len );"
        }
      ]
    ]
  },
  {
    "type": "macro",
    "lines": [
      [
        {
          "type": "MACRO_BLOCK",
          "content": ".BI",
          "translatable": false
        },
        {
          "type": "TEXT",
          "content": " \"int NLMSG_LENGTH(size_t \" len );"
        }
      ]
    ]
  },
  {
    "type": "macro",
    "lines": [
      [
        {
          "type": "MACRO_BLOCK",
          "content": ".BI",
          "translatable": false
        },
        {
          "type": "TEXT",
          "content": " \"int NLMSG_SPACE(size_t \" len );"
        }
      ]
    ]
  },
  {
    "type": "macro",
    "lines": [
      [
        {
          "type": "MACRO_BLOCK",
          "content": ".BI",
          "translatable": false
        },
        {
          "type": "TEXT",
          "content": " \"void *NLMSG_DATA(struct nlmsghdr *\" nlh );"
        }
      ]
    ]
  },
  {
    "type": "macro",
    "lines": [
      [
        {
          "type": "MACRO_BLOCK",
          "content": ".BI",
          "translatable": false
        },
        {
          "type": "TEXT",
          "content": " \"struct nlmsghdr *NLMSG_NEXT(struct nlmsghdr *\" nlh \", int \" len );"
        }
      ]
    ]
  },
  {
    "type": "macro",
    "lines": [
      [
        {
          "type": "MACRO_BLOCK",
          "content": ".BI",
          "translatable": false
        },
        {
          "type": "TEXT",
          "content": " \"int NLMSG_OK(struct nlmsghdr *\" nlh \", int \" len );"
        }
      ]
    ]
  },
  {
    "type": "macro",
    "lines": [
      [
        {
          "type": "MACRO_BLOCK",
          "content": ".BI",
          "translatable": false
        },
        {
          "type": "TEXT",
          "content": " \"int NLMSG_PAYLOAD(struct nlmsghdr *\" nlh \", int \" len );"
        }
      ]
    ]
  },
  {
    "type": "macro",
    "lines": [
      [
        {
          "type": "MACRO_BLOCK",
          "content": ".fi",
          "translatable": false
        }
      ]
    ]
  },
  {
    "type": "macro",
    "lines": [
      [
        {
          "type": "MACRO_BLOCK",
          "content": ".SH",
          "translatable": true
        },
        {
          "type": "TEXT",
          "content": " DESCRIPTION"
        }
      ]
    ]
  },
  {
    "type": "content",
    "lines": [
      [
        {
          "type": "MACRO_INLINE",
          "content": ".I",
          "translatable": false
        },
        {
          "type": "TEXT",
          "content": " <linux/netlink.h>"
        }
      ],
      [
        {
          "type": "TEXT",
          "content": "defines several standard macros to access or create a netlink datagram."
        }
      ],
      [
        {
          "type": "TEXT",
          "content": "They are similar in spirit to the macros defined in"
        }
      ],
      [
        {
          "type": "MACRO_INLINE",
          "content": ".BR",
          "translatable": false
        },
        {
          "type": "TEXT",
          "content": " cmsg (3)"
        }
      ],
      [
        {
          "type": "TEXT",
          "content": "for auxiliary data."
        }
      ],
      [
        {
          "type": "TEXT",
          "content": "The buffer passed to and from a netlink socket should"
        }
      ],
      [
        {
          "type": "TEXT",
          "content": "be accessed using only these macros."
        }
      ]
    ]
  },
  {
    "type": "macro",
    "lines": [
      [
        {
          "type": "MACRO_BLOCK",
          "content": ".TP",
          "translatable": false
        }
      ]
    ]
  },
  {
    "type": "content",
    "lines": [
      [
        {
          "type": "MACRO_INLINE",
          "content": ".BR",
          "translatable": false
        },
        {
          "type": "TEXT",
          "content": " NLMSG_ALIGN ()"
        }
      ],
      [
        {
          "type": "TEXT",
          "content": "Round the length of a netlink message up to align it properly."
        }
      ]
    ]
  },
  {
    "type": "macro",
    "lines": [
      [
        {
          "type": "MACRO_BLOCK",
          "content": ".TP",
          "translatable": false
        }
      ]
    ]
  },
  {
    "type": "content",
    "lines": [
      [
        {
          "type": "MACRO_INLINE",
          "content": ".BR",
          "translatable": false
        },
        {
          "type": "TEXT",
          "content": " NLMSG_LENGTH ()"
        }
      ],
      [
        {
          "type": "TEXT",
          "content": "Given the payload length,"
        }
      ],
      [
        {
          "type": "MACRO_INLINE",
          "content": ".IR",
          "translatable": false
        },
        {
          "type": "TEXT",
          "content": " len ,"
        }
      ],
      [
        {
          "type": "TEXT",
          "content": "this macro returns the aligned length to store in the"
        }
      ],
      [
        {
          "type": "MACRO_INLINE",
          "content": ".I",
          "translatable": false
        },
        {
          "type": "TEXT",
          "content": " nlmsg_len"
        }
      ],
      [
        {
          "type": "TEXT",
          "content": "field of the"
        }
      ],
      [
        {
          "type": "MACRO_INLINE",
          "content": ".IR",
          "translatable": false
        },
        {
          "type": "TEXT",
          "content": " nlmsghdr ."
        }
      ]
    ]
  },
  {
    "type": "macro",
    "lines": [
      [
        {
          "type": "MACRO_BLOCK",
          "content": ".TP",
          "translatable": false
        }
      ]
    ]
  },
  {
    "type": "content",
    "lines": [
      [
        {
          "type": "MACRO_INLINE",
          "content": ".BR",
          "translatable": false
        },
        {
          "type": "TEXT",
          "content": " NLMSG_SPACE ()"
        }
      ],
      [
        {
          "type": "TEXT",
          "content": "Return the number of bytes that a netlink message with payload of"
        }
      ],
      [
        {
          "type": "MACRO_INLINE",
          "content": ".I",
          "translatable": false
        },
        {
          "type": "TEXT",
          "content": " len"
        }
      ],
      [
        {
          "type": "TEXT",
          "content": "would occupy."
        }
      ]
    ]
  },
  {
    "type": "macro",
    "lines": [
      [
        {
          "type": "MACRO_BLOCK",
          "content": ".TP",
          "translatable": false
        }
      ]
    ]
  },
  {
    "type": "content",
    "lines": [
      [
        {
          "type": "MACRO_INLINE",
          "content": ".BR",
          "translatable": false
        },
        {
          "type": "TEXT",
          "content": " NLMSG_DATA ()"
        }
      ],
      [
        {
          "type": "TEXT",
          "content": "Return a pointer to the payload associated with the passed"
        }
      ],
      [
        {
          "type": "MACRO_INLINE",
          "content": ".IR",
          "translatable": false
        },
        {
          "type": "TEXT",
          "content": " nlmsghdr ."
        }
      ]
    ]
  },
  {
    "type": "macro",
    "lines": [
      [
        {
          "type": "MACRO_BLOCK",
          "content": ".TP",
          "translatable": false
        }
      ]
    ]
  },
  {
    "type": "comment",
    "lines": [
      [
        {
          "type": "COMMENT_BLOCK",
          "content": ".\\\" this is bizarre, maybe the interface should be fixed."
        }
      ]
    ]
  },
  {
    "type": "content",
    "lines": [
      [
        {
          "type": "MACRO_INLINE",
          "content": ".BR",
          "translatable": false
        },
        {
          "type": "TEXT",
          "content": " NLMSG_NEXT ()"
        }
      ],
      [
        {
          "type": "TEXT",
          "content": "Get the next"
        }
      ],
      [
        {
          "type": "MACRO_INLINE",
          "content": ".I",
          "translatable": false
        },
        {
          "type": "TEXT",
          "content": " nlmsghdr"
        }
      ],
      [
        {
          "type": "TEXT",
          "content": "in a multipart message."
        }
      ],
      [
        {
          "type": "TEXT",
          "content": "The caller must check if the current"
        }
      ],
      [
        {
          "type": "MACRO_INLINE",
          "content": ".I",
          "translatable": false
        },
        {
          "type": "TEXT",
          "content": " nlmsghdr"
        }
      ],
      [
        {
          "type": "TEXT",
          "content": "didn't have the"
        }
      ],
      [
        {
          "type": "MACRO_INLINE",
          "content": ".B",
          "translatable": false
        },
        {
          "type": "TEXT",
          "content": " NLMSG_DONE"
        }
      ],
      [
        {
          "type": "TEXT",
          "content": "set"
        },
        {
          "type": "ESCAPE",
          "content": "\\(em"
        },
        {
          "type": "TEXT",
          "content": "this function doesn't return NULL on end."
        }
      ],
      [
        {
          "type": "TEXT",
          "content": "The"
        }
      ],
      [
        {
          "type": "MACRO_INLINE",
          "content": ".I",
          "translatable": false
        },
        {
          "type": "TEXT",
          "content": " len"
        }
      ],
      [
        {
          "type": "TEXT",
          "content": "argument is an lvalue containing the remaining length"
        }
      ],
      [
        {
          "type": "TEXT",
          "content": "of the message buffer."
        }
      ],
      [
        {
          "type": "TEXT",
          "content": "This macro decrements it by the length of the message header."
        }
      ]
    ]
  },
  {
    "type": "macro",
    "lines": [
      [
        {
          "type": "MACRO_BLOCK",
          "content": ".TP",
          "translatable": false
        }
      ]
    ]
  },
  {
    "type": "content",
    "lines": [
      [
        {
          "type": "MACRO_INLINE",
          "content": ".BR",
          "translatable": false
        },
        {
          "type": "TEXT",
          "content": " NLMSG_OK ()"
        }
      ],
      [
        {
          "type": "TEXT",
          "content": "Return true if the netlink message is not truncated and"
        }
      ],
      [
        {
          "type": "TEXT",
          "content": "is in a form suitable for parsing."
        }
      ]
    ]
  },
  {
    "type": "macro",
    "lines": [
      [
        {
          "type": "MACRO_BLOCK",
          "content": ".TP",
          "translatable": false
        }
      ]
    ]
  },
  {
    "type": "content",
    "lines": [
      [
        {
          "type": "MACRO_INLINE",
          "content": ".BR",
          "translatable": false
        },
        {
          "type": "TEXT",
          "content": " NLMSG_PAYLOAD ()"
        }
      ],
      [
        {
          "type": "TEXT",
          "content": "Return the length of the payload associated with the"
        }
      ],
      [
        {
          "type": "MACRO_INLINE",
          "content": ".IR",
          "translatable": false
        },
        {
          "type": "TEXT",
          "content": " nlmsghdr ."
        }
      ]
    ]
  },
  {
    "type": "macro",
    "lines": [
      [
        {
          "type": "MACRO_BLOCK",
          "content": ".SH",
          "translatable": true
        },
        {
          "type": "TEXT",
          "content": " CONFORMING TO"
        }
      ]
    ]
  },
  {
    "type": "content",
    "lines": [
      [
        {
          "type": "TEXT",
          "content": "These macros are nonstandard Linux extensions."
        }
      ]
    ]
  },
  {
    "type": "macro",
    "lines": [
      [
        {
          "type": "MACRO_BLOCK",
          "content": ".SH",
          "translatable": true
        },
        {
          "type": "TEXT",
          "content": " NOTES"
        }
      ]
    ]
  },
  {
    "type": "content",
    "lines": [
      [
        {
          "type": "TEXT",
          "content": "It is often better to use netlink via"
        }
      ],
      [
        {
          "type": "MACRO_INLINE",
          "content": ".I",
          "translatable": false
        },
        {
          "type": "TEXT",
          "content": " libnetlink"
        }
      ],
      [
        {
          "type": "TEXT",
          "content": "than via the low-level kernel interface."
        }
      ]
    ]
  },
  {
    "type": "macro",
    "lines": [
      [
        {
          "type": "MACRO_BLOCK",
          "content": ".SH",
          "translatable": true
        },
        {
          "type": "TEXT",
          "content": " SEE ALSO"
        }
      ]
    ]
  },
  {
    "type": "content",
    "lines": [
      [
        {
          "type": "MACRO_INLINE",
          "content": ".BR",
          "translatable": false
        },
        {
          "type": "TEXT",
          "content": " libnetlink (3),"
        }
      ],
      [
        {
          "type": "MACRO_INLINE",
          "content": ".BR",
          "translatable": false
        },
        {
          "type": "TEXT",
          "content": " netlink (7)"
        }
      ]
    ]
  }
]
